LICENSE.txt
MANIFEST.in
README.txt
setup.py
django_resources.egg-info/PKG-INFO
django_resources.egg-info/SOURCES.txt
django_resources.egg-info/dependency_links.txt
django_resources.egg-info/namespace_packages.txt
django_resources.egg-info/not-zip-safe
django_resources.egg-info/requires.txt
django_resources.egg-info/top_level.txt
resources/__init__.py
resources/admin.py
resources/config.py
resources/models.py
resources/tests.py
resources/urls.py
resources/utils.py
resources/views.py
resources/templates/resources/css.html
resources/templates/resources/javascript.html
resources/templates/resources/resources.html
resources/templatetags/__init__.py
resources/templatetags/resources_tags.py