Metadata-Version: 1.0
Name: django-resources
Version: 1.0a1
Summary: CSS and Javascript management for Django.
Home-page: http://www.iqpp.de
Author: Kai Diefenbach
Author-email: kai.diefenbach@iqpp.de
License: BSD
Keywords: django css javascript
Platform: UNKNOWN
Classifier: Development Status :: 4 - Beta
Classifier: Environment :: Web Environment
Classifier: Framework :: Django
Classifier: License :: OSI Approved :: BSD License
Classifier: Operating System :: OS Independent
Classifier: Programming Language :: Python
